pypesh/__init__.py
pypesh/__main__.py
pypesh/analytic.py
pypesh/fem.py
pypesh/generate_mesh.py
pypesh/pesh.py
pypesh/stokes_flow.py
pypesh/trajectories.py
pypesh/visualisation.py
pypesh/data/pesh.csv
pypesh-0.1.5.dist-info/LICENSE
pypesh-0.1.5.dist-info/METADATA
pypesh-0.1.5.dist-info/WHEEL
pypesh-0.1.5.dist-info/top_level.txt
pypesh-0.1.5.dist-info/RECORD
