Metadata-Version: 2.1
Name: pypesh
Version: 0.1.5
Summary: Sherwood number in Stokes flow
Home-page: https://github.com/turczyneq/pypesh
Author: Jan Turczynowicz and Radost Waszkiewicz
Author-email: turczynowicz.jan@wp.pl
License: GNU GPLv3
Project-URL: Documentation, https://pypesh.readthedocs.io
Project-URL: Source, https://github.com/turczyneq/pypesh/
Platform: UNKNOWN
License-File: LICENSE
Requires-Dist: matplotlib
Requires-Dist: numpy
Requires-Dist: pychastic
Requires-Dist: pygmsh
Requires-Dist: scikit-fem
Requires-Dist: scipy
